{"Name":"Resource","TypeInfo":"Tasha.Common.Resource, Tasha, Version=1.0.0.0, Culture=neutral, PublicKeyToken=null","TypeName":"Tasha.Common.Resource","AssemblyInfo":{"Data":"Tasha, Version=1.0.0.0, Culture=neutral, PublicKeyToken=null","UnityType":6,"AssemblyName":"Tasha, Version=1.0.0.0, Culture=neutral, PublicKeyToken=null"},"ParameterPropertyMetaInfo":[{"Attributes":[{"Index":0,"AttachedToField":false,"DefaultValue":"UniqueName","Description":"The unique name for this resource.","Name":"Resource Name","VariableName":null,"TypeId":"XTMF.RunParameterAttribute, XTMFInterfaces, Version=1.0.0.0, Culture=neutral, PublicKeyToken=null"}],"PropertyInfo":{"Name":"ResourceName","AssemblyName":"Tasha, Version=1.0.0.0, Culture=neutral, PublicKeyToken=null","ClassName":"Tasha.Common.Resource","Signature":"System.String ResourceName","Signature2":"System.String ResourceName","MemberType":16,"GenericArguments":null}}],"SubModulePropertyMetaInfo":[],"ModuleInfo":null}