{"Name":"TimePeriodNetworkData","TypeInfo":"Tasha.Network.V4AutoNetwork+TimePeriodNetworkData, Tasha, Version=1.0.0.0, Culture=neutral, PublicKeyToken=null","TypeName":"Tasha.Network.V4AutoNetwork+TimePeriodNetworkData","AssemblyInfo":{"Data":"Tasha, Version=1.0.0.0, Culture=neutral, PublicKeyToken=null","UnityType":6,"AssemblyName":"Tasha, Version=1.0.0.0, Culture=neutral, PublicKeyToken=null"},"ParameterPropertyMetaInfo":[],"SubModulePropertyMetaInfo":[],"ModuleInfo":{"Description":"This module defines a time period and store the network data for that time period.  Implemented first for GTAModel V4.0.","IconURI":null,"Name":null,"DocURL":null,"TypeId":"XTMF.ModuleInformationAttribute, XTMFInterfaces, Version=1.0.0.0, Culture=neutral, PublicKeyToken=null"},"DisplayName":"V4AutoNetwork+TimePeriodNetworkData"}